[{"company":"Realcube","position":"Human Resources Manager","jobLocation":"Qiulu","jobStatus":"pending","createdAt":"2023-09-17T02:18:36Z","jobType":"full-time"},
{"company":"Twitterlist","position":"Occupational Therapist","jobLocation":"Kitwe","jobStatus":"pending","createdAt":"2023-02-21T04:23:55Z","jobType":"internship"},
{"company":"Realcube","position":"Information Systems Manager","jobLocation":"Si Wilai","jobStatus":"pending","createdAt":"2023-04-24T07:08:25Z","jobType":"part-time"},
{"company":"Vinder","position":"Nuclear Power Engineer","jobLocation":"Utama Wetan","jobStatus":"declined","createdAt":"2023-08-10T07:24:46Z","jobType":"full-time"},
{"company":"Photobug","position":"Project Manager","jobLocation":"Dongting","jobStatus":"interview","createdAt":"2023-02-08T21:37:08Z","jobType":"internship"},
{"company":"Jetwire","position":"Database Administrator II","jobLocation":"Guandukou","jobStatus":"declined","createdAt":"2023-08-28T17:38:10Z","jobType":"internship"},
{"company":"Jamia","position":"Cost Accountant","jobLocation":"Xinmin","jobStatus":"declined","createdAt":"2023-05-08T08:46:07Z","jobType":"full-time"},
{"company":"Twimbo","position":"Accountant III","jobLocation":"Saatlı","jobStatus":"pending","createdAt":"2023-04-20T00:34:26Z","jobType":"full-time"},
{"company":"Chatterpoint","position":"Registered Nurse","jobLocation":"Tunggulsari","jobStatus":"declined","createdAt":"2023-06-12T17:12:41Z","jobType":"part-time"},
{"company":"Realbridge","position":"Desktop Support Technician","jobLocation":"Kushchëvskaya","jobStatus":"interview","createdAt":"2023-06-24T21:57:40Z","jobType":"internship"},
{"company":"Linkbuzz","position":"Structural Engineer","jobLocation":"Marugame","jobStatus":"pending","createdAt":"2023-09-13T07:29:42Z","jobType":"part-time"},
{"company":"Skinte","position":"Computer Systems Analyst II","jobLocation":"Zhenxi","jobStatus":"pending","createdAt":"2023-02-25T01:32:35Z","jobType":"internship"},
{"company":"Jabbersphere","position":"Software Consultant","jobLocation":"Isla Verde","jobStatus":"interview","createdAt":"2023-06-19T01:03:59Z","jobType":"full-time"},
{"company":"Gabtype","position":"Senior Financial Analyst","jobLocation":"Ballymun","jobStatus":"pending","createdAt":"2023-02-14T05:29:06Z","jobType":"internship"},
{"company":"Oba","position":"Analyst Programmer","jobLocation":"Fuxing","jobStatus":"pending","createdAt":"2022-12-13T08:03:13Z","jobType":"internship"},
{"company":"Mita","position":"Health Coach II","jobLocation":"Yenangyaung","jobStatus":"pending","createdAt":"2023-09-03T15:32:57Z","jobType":"full-time"},
{"company":"Photospace","position":"Dental Hygienist","jobLocation":"Resistencia","jobStatus":"pending","createdAt":"2023-07-16T01:36:34Z","jobType":"full-time"},
{"company":"Skyndu","position":"Recruiting Manager","jobLocation":"Kalininskiy","jobStatus":"declined","createdAt":"2022-11-20T13:57:54Z","jobType":"part-time"},
{"company":"Tambee","position":"Database Administrator IV","jobLocation":"Portland","jobStatus":"pending","createdAt":"2023-08-28T17:58:45Z","jobType":"part-time"},
{"company":"Trunyx","position":"Food Chemist","jobLocation":"Hamburg","jobStatus":"declined","createdAt":"2023-06-16T14:00:55Z","jobType":"internship"},
{"company":"Skinte","position":"Project Manager","jobLocation":"Punat","jobStatus":"declined","createdAt":"2023-08-08T08:28:40Z","jobType":"part-time"},
{"company":"Oyoyo","position":"Internal Auditor","jobLocation":"Ploso Wetan","jobStatus":"declined","createdAt":"2023-06-30T23:07:07Z","jobType":"full-time"},
{"company":"Ooba","position":"Health Coach III","jobLocation":"Tangxia","jobStatus":"pending","createdAt":"2023-01-02T21:28:02Z","jobType":"full-time"},
{"company":"Jabberstorm","position":"Associate Professor","jobLocation":"Sumurgayam","jobStatus":"pending","createdAt":"2023-08-03T15:38:36Z","jobType":"part-time"},
{"company":"Centidel","position":"VP Sales","jobLocation":"Gainesville","jobStatus":"pending","createdAt":"2022-12-19T11:48:00Z","jobType":"internship"},
{"company":"Centizu","position":"Software Consultant","jobLocation":"Lanchyn","jobStatus":"declined","createdAt":"2023-01-23T23:15:56Z","jobType":"part-time"},
{"company":"Dabfeed","position":"Desktop Support Technician","jobLocation":"Pan-an","jobStatus":"interview","createdAt":"2023-02-05T15:59:55Z","jobType":"full-time"},
{"company":"Innojam","position":"Business Systems Development Analyst","jobLocation":"Jabonga","jobStatus":"declined","createdAt":"2023-03-07T01:44:12Z","jobType":"internship"},
{"company":"Yodo","position":"Internal Auditor","jobLocation":"Farap","jobStatus":"declined","createdAt":"2022-10-26T08:51:18Z","jobType":"full-time"},
{"company":"Roombo","position":"Senior Quality Engineer","jobLocation":"Manoc-Manoc","jobStatus":"interview","createdAt":"2023-02-22T05:11:27Z","jobType":"part-time"},
{"company":"Centimia","position":"Senior Financial Analyst","jobLocation":"Bernardo Larroudé","jobStatus":"declined","createdAt":"2023-02-18T22:11:58Z","jobType":"full-time"},
{"company":"Twitterworks","position":"VP Quality Control","jobLocation":"Bahaodi","jobStatus":"pending","createdAt":"2022-11-29T08:22:47Z","jobType":"internship"},
{"company":"Rhynyx","position":"Cost Accountant","jobLocation":"Cikadu","jobStatus":"pending","createdAt":"2023-07-19T09:51:53Z","jobType":"full-time"},
{"company":"Yabox","position":"Web Developer III","jobLocation":"Houston","jobStatus":"declined","createdAt":"2023-09-19T01:58:31Z","jobType":"part-time"},
{"company":"Quimm","position":"Graphic Designer","jobLocation":"Tilburg","jobStatus":"pending","createdAt":"2023-08-19T09:50:35Z","jobType":"internship"},
{"company":"Thoughtsphere","position":"Technical Writer","jobLocation":"Mercier","jobStatus":"interview","createdAt":"2023-01-30T10:58:15Z","jobType":"full-time"},
{"company":"Rhynoodle","position":"Actuary","jobLocation":"Chisht-e Sharīf","jobStatus":"pending","createdAt":"2023-06-10T23:40:32Z","jobType":"internship"},
{"company":"Dynabox","position":"Physical Therapy Assistant","jobLocation":"Xiayang","jobStatus":"pending","createdAt":"2022-11-06T15:04:38Z","jobType":"full-time"},
{"company":"Voomm","position":"Sales Representative","jobLocation":"Guankou","jobStatus":"declined","createdAt":"2023-08-22T16:54:11Z","jobType":"part-time"},
{"company":"Trupe","position":"Nurse","jobLocation":"Cisantri","jobStatus":"declined","createdAt":"2023-05-15T21:08:56Z","jobType":"full-time"},
{"company":"Janyx","position":"Software Engineer IV","jobLocation":"Mancogeh","jobStatus":"pending","createdAt":"2023-04-22T17:38:57Z","jobType":"internship"},
{"company":"Fanoodle","position":"Junior Executive","jobLocation":"Maputsoe","jobStatus":"interview","createdAt":"2023-02-06T13:10:16Z","jobType":"part-time"},
{"company":"Blogpad","position":"Graphic Designer","jobLocation":"Kakogawachō-honmachi","jobStatus":"interview","createdAt":"2022-12-01T03:26:16Z","jobType":"internship"},
{"company":"Youbridge","position":"Executive Secretary","jobLocation":"Cataguases","jobStatus":"interview","createdAt":"2022-11-25T18:38:11Z","jobType":"full-time"},
{"company":"Quatz","position":"Help Desk Technician","jobLocation":"Yanyang","jobStatus":"interview","createdAt":"2023-08-12T21:44:26Z","jobType":"internship"},
{"company":"Blogspan","position":"Project Manager","jobLocation":"Kotanopan","jobStatus":"declined","createdAt":"2023-03-20T19:28:05Z","jobType":"part-time"},
{"company":"Divanoodle","position":"Occupational Therapist","jobLocation":"Klapagada","jobStatus":"declined","createdAt":"2023-07-07T11:03:38Z","jobType":"part-time"},
{"company":"Eamia","position":"Senior Cost Accountant","jobLocation":"Jiangyin","jobStatus":"declined","createdAt":"2023-02-27T17:37:59Z","jobType":"part-time"},
{"company":"Chatterbridge","position":"Environmental Tech","jobLocation":"Krajan Selatan","jobStatus":"interview","createdAt":"2023-05-01T00:09:20Z","jobType":"full-time"},
{"company":"Bubbletube","position":"Dental Hygienist","jobLocation":"Dordrecht","jobStatus":"declined","createdAt":"2023-07-26T19:46:47Z","jobType":"part-time"},
{"company":"Yodel","position":"Associate Professor","jobLocation":"Tianning","jobStatus":"pending","createdAt":"2023-01-16T16:23:03Z","jobType":"part-time"},
{"company":"Linklinks","position":"VP Marketing","jobLocation":"Qingshandi","jobStatus":"pending","createdAt":"2023-07-19T14:01:14Z","jobType":"part-time"},
{"company":"Edgeblab","position":"Environmental Tech","jobLocation":"Kristiansand S","jobStatus":"pending","createdAt":"2023-03-30T23:21:49Z","jobType":"full-time"},
{"company":"Livetube","position":"Desktop Support Technician","jobLocation":"Ciparasi","jobStatus":"interview","createdAt":"2023-06-20T19:38:38Z","jobType":"full-time"},
{"company":"Reallinks","position":"Graphic Designer","jobLocation":"Zlataritsa","jobStatus":"interview","createdAt":"2023-03-10T11:34:05Z","jobType":"full-time"},
{"company":"Jabbertype","position":"Nuclear Power Engineer","jobLocation":"Quba","jobStatus":"pending","createdAt":"2022-12-03T09:06:58Z","jobType":"internship"},
{"company":"Bluejam","position":"Automation Specialist IV","jobLocation":"Yaozhanzi","jobStatus":"declined","createdAt":"2022-10-04T06:28:20Z","jobType":"internship"},
{"company":"Dabvine","position":"Community Outreach Specialist","jobLocation":"Baguim do Monte","jobStatus":"interview","createdAt":"2023-01-27T07:19:52Z","jobType":"internship"},
{"company":"Bubblebox","position":"Staff Scientist","jobLocation":"Fontainhas","jobStatus":"interview","createdAt":"2023-05-08T04:18:01Z","jobType":"internship"},
{"company":"Zoonoodle","position":"Internal Auditor","jobLocation":"Bourges","jobStatus":"pending","createdAt":"2022-12-17T12:03:51Z","jobType":"internship"},
{"company":"Aimbu","position":"Data Coordinator","jobLocation":"Maodian","jobStatus":"interview","createdAt":"2023-06-07T01:20:01Z","jobType":"part-time"},
{"company":"Kayveo","position":"Systems Administrator III","jobLocation":"Basen","jobStatus":"pending","createdAt":"2023-08-11T05:50:29Z","jobType":"full-time"},
{"company":"Gabtune","position":"Information Systems Manager","jobLocation":"Wangzuizi","jobStatus":"declined","createdAt":"2022-11-04T14:28:07Z","jobType":"full-time"},
{"company":"Quamba","position":"Safety Technician III","jobLocation":"Xicheng","jobStatus":"interview","createdAt":"2022-11-17T15:55:43Z","jobType":"full-time"},
{"company":"Fivechat","position":"GIS Technical Architect","jobLocation":"Jardim da Serra","jobStatus":"declined","createdAt":"2023-04-07T05:36:36Z","jobType":"internship"},
{"company":"Photolist","position":"VP Marketing","jobLocation":"Machagai","jobStatus":"declined","createdAt":"2023-05-20T16:09:13Z","jobType":"internship"},
{"company":"Aibox","position":"Staff Scientist","jobLocation":"Yanglinqiao","jobStatus":"interview","createdAt":"2023-04-22T14:38:11Z","jobType":"part-time"},
{"company":"Skivee","position":"VP Quality Control","jobLocation":"Khust","jobStatus":"pending","createdAt":"2022-11-29T22:38:23Z","jobType":"part-time"},
{"company":"Yacero","position":"Project Manager","jobLocation":"Zürich","jobStatus":"interview","createdAt":"2023-01-08T03:37:54Z","jobType":"full-time"},
{"company":"Podcat","position":"VP Marketing","jobLocation":"May Pen","jobStatus":"declined","createdAt":"2023-09-17T12:04:29Z","jobType":"full-time"},
{"company":"Wikivu","position":"Dental Hygienist","jobLocation":"Tiền Hải","jobStatus":"pending","createdAt":"2023-01-12T05:31:50Z","jobType":"internship"},
{"company":"Dabfeed","position":"General Manager","jobLocation":"Krajan Jabungcandi","jobStatus":"pending","createdAt":"2023-06-17T13:13:16Z","jobType":"part-time"},
{"company":"Jaloo","position":"Engineer IV","jobLocation":"Negeriagung","jobStatus":"declined","createdAt":"2022-11-09T17:18:39Z","jobType":"full-time"},
{"company":"Demivee","position":"Senior Sales Associate","jobLocation":"Psachná","jobStatus":"pending","createdAt":"2023-04-15T07:37:39Z","jobType":"full-time"},
{"company":"Podcat","position":"Information Systems Manager","jobLocation":"Niutang","jobStatus":"interview","createdAt":"2023-05-26T22:13:58Z","jobType":"internship"},
{"company":"Shuffletag","position":"Product Engineer","jobLocation":"Lyon","jobStatus":"interview","createdAt":"2023-02-04T14:34:53Z","jobType":"full-time"},
{"company":"Minyx","position":"Web Developer II","jobLocation":"Conchucos","jobStatus":"interview","createdAt":"2023-05-05T07:38:42Z","jobType":"full-time"},
{"company":"Realmix","position":"Quality Control Specialist","jobLocation":"Grand Rapids","jobStatus":"interview","createdAt":"2022-10-21T13:36:01Z","jobType":"part-time"},
{"company":"Edgeblab","position":"Product Engineer","jobLocation":"Hwawŏn","jobStatus":"pending","createdAt":"2022-11-14T08:47:16Z","jobType":"full-time"},
{"company":"Ooba","position":"Automation Specialist II","jobLocation":"Gunungkendeng","jobStatus":"declined","createdAt":"2023-01-18T00:15:08Z","jobType":"full-time"},
{"company":"Trudeo","position":"Analog Circuit Design manager","jobLocation":"Pisões","jobStatus":"declined","createdAt":"2022-12-24T02:09:44Z","jobType":"internship"},
{"company":"Twitterbridge","position":"Web Developer II","jobLocation":"Zhangdian","jobStatus":"interview","createdAt":"2023-02-01T13:50:41Z","jobType":"part-time"},
{"company":"Skyba","position":"Health Coach III","jobLocation":"Tunjë","jobStatus":"interview","createdAt":"2023-06-01T19:09:31Z","jobType":"full-time"},
{"company":"Twitterworks","position":"Payment Adjustment Coordinator","jobLocation":"San Vicente","jobStatus":"pending","createdAt":"2023-05-03T08:08:11Z","jobType":"part-time"},
{"company":"Npath","position":"VP Sales","jobLocation":"Luar","jobStatus":"declined","createdAt":"2023-07-29T02:43:17Z","jobType":"internship"},
{"company":"Flashspan","position":"Chemical Engineer","jobLocation":"Dushanbe","jobStatus":"interview","createdAt":"2023-06-07T11:01:12Z","jobType":"part-time"},
{"company":"Vipe","position":"Senior Cost Accountant","jobLocation":"Nakusp","jobStatus":"pending","createdAt":"2023-07-06T09:33:11Z","jobType":"full-time"},
{"company":"Yodel","position":"Web Designer I","jobLocation":"Anren","jobStatus":"pending","createdAt":"2023-06-02T07:47:33Z","jobType":"part-time"},
{"company":"Yata","position":"Geologist II","jobLocation":"Butha-Buthe","jobStatus":"pending","createdAt":"2022-10-11T23:03:04Z","jobType":"part-time"},
{"company":"Tavu","position":"Professor","jobLocation":"Kota Kinabalu","jobStatus":"interview","createdAt":"2023-06-07T13:43:34Z","jobType":"internship"},
{"company":"Oodoo","position":"Engineer IV","jobLocation":"Meybod","jobStatus":"declined","createdAt":"2023-06-14T21:48:29Z","jobType":"internship"},
{"company":"Brainlounge","position":"Programmer I","jobLocation":"Chongjin","jobStatus":"interview","createdAt":"2023-04-28T04:44:46Z","jobType":"part-time"},
{"company":"Devshare","position":"Health Coach III","jobLocation":"Gucheng","jobStatus":"interview","createdAt":"2022-10-31T19:55:49Z","jobType":"internship"},
{"company":"Innotype","position":"Legal Assistant","jobLocation":"Palekastro","jobStatus":"pending","createdAt":"2023-01-29T21:25:35Z","jobType":"part-time"},
{"company":"Meevee","position":"Chemical Engineer","jobLocation":"Diego de Almagro","jobStatus":"declined","createdAt":"2023-01-08T06:33:05Z","jobType":"part-time"},
{"company":"Snaptags","position":"Programmer III","jobLocation":"Petropavlovka","jobStatus":"pending","createdAt":"2023-01-30T07:23:20Z","jobType":"full-time"},
{"company":"Vinder","position":"Professor","jobLocation":"Zolochiv","jobStatus":"declined","createdAt":"2023-09-07T09:21:22Z","jobType":"part-time"},
{"company":"Skibox","position":"Systems Administrator II","jobLocation":"Ash Shaḩānīyah","jobStatus":"interview","createdAt":"2022-11-26T22:53:17Z","jobType":"full-time"},
{"company":"Flashspan","position":"Actuary","jobLocation":"Bataiporã","jobStatus":"pending","createdAt":"2023-06-12T19:38:21Z","jobType":"full-time"},
{"company":"Topicware","position":"Senior Sales Associate","jobLocation":"Mikrókampos","jobStatus":"pending","createdAt":"2023-06-27T12:44:40Z","jobType":"part-time"}]